ab_core/token_store/__init__.py
ab_core/token_store/oauth2/schema/__init__.py
ab_core/token_store/oauth2/schema/store_type.py
ab_core/token_store/oauth2/store/__init__.py
ab_core/token_store/oauth2/store/base.py
ab_core/token_store/oauth2/store/database.py
ab_core/token_store/oauth2/store/fs.py
ab_core/token_store/oauth2/store/template.py
ab_token_store-0.1.4.dist-info/METADATA
ab_token_store-0.1.4.dist-info/WHEEL
ab_token_store-0.1.4.dist-info/licenses/LICENSE
ab_token_store-0.1.4.dist-info/RECORD
