Metadata-Version: 2.4
Name: ab-token-store
Version: 0.1.4
Author-email: Matthew Coulter <53892067+mattcoulter7@users.noreply.github.com>
License-File: LICENSE
Requires-Python: <4,>=3.12
Requires-Dist: ab-auth-client<1,>=0.1.3
Requires-Dist: ab-database<1,>=0.1.3
Requires-Dist: ab-dependency<1,>=0.1.4
